<?xml version="1.0" encoding="UTF-8"?>
<mxGraphModel dx="1552" dy="872" grid="1" gridSize="10" guides="1" tooltips="1" connect="1" arrows="1" fold="1" page="1" pageScale="1" pageWidth="1520" pageHeight="1520" background="#ffffff" math="0" shadow="0"><root><mxCell id="0"/><mxCell id="1" parent="0"/><mxCell id="2e49270ec7c68f3f-1" value="Task" style="swimlane;html=1;fontStyle=0;childLayout=stackLayout;horizontal=1;startSize=26;fillColor=#f8cecc;horizontalStack=0;resizeParent=1;resizeLast=0;collapsible=1;marginBottom=0;swimlaneFillColor=#ffffff;align=center;rounded=0;shadow=0;comic=0;labelBackgroundColor=none;strokeColor=#b85450;strokeWidth=1;fontFamily=Verdana;fontSize=14;fontColor=#000000;" parent="1" vertex="1"><mxGeometry x="441" y="401" width="199" height="454" as="geometry"/></mxCell><mxCell id="156" style="edgeStyle=orthogonalEdgeStyle;rounded=0;html=1;exitX=1;exitY=0.5;entryX=1;entryY=0.5;startArrow=ERone;startFill=0;endArrow=ERoneToMany;endFill=0;jettySize=auto;orthogonalLoop=1;" edge="1" parent="2e49270ec7c68f3f-1" source="2e49270ec7c68f3f-4" target="152"><mxGeometry relative="1" as="geometry"><Array as="points"><mxPoint x="239" y="41"/><mxPoint x="239" y="321"/></Array></mxGeometry></mxCell><mxCell id="157" style="edgeStyle=orthogonalEdgeStyle;rounded=0;html=1;exitX=1;exitY=0.5;startArrow=ERone;startFill=0;endArrow=ERoneToMany;endFill=0;jettySize=auto;orthogonalLoop=1;" edge="1" parent="2e49270ec7c68f3f-1" source="2e49270ec7c68f3f-4"><mxGeometry relative="1" as="geometry"><mxPoint x="199" y="359" as="targetPoint"/><Array as="points"><mxPoint x="279" y="41"/><mxPoint x="279" y="359"/></Array></mxGeometry></mxCell><mxCell id="2e49270ec7c68f3f-4" value="uniqueId" style="shape=partialRectangle;top=0;left=0;right=0;bottom=1;html=1;align=left;verticalAlign=middle;fillColor=none;spacingLeft=60;spacingRight=4;whiteSpace=wrap;overflow=hidden;rotatable=0;points=[[0,0.5],[1,0.5]];portConstraint=eastwest;dropTarget=0;fontStyle=5;" parent="2e49270ec7c68f3f-1" vertex="1"><mxGeometry y="26" width="199" height="30" as="geometry"/></mxCell><mxCell id="2e49270ec7c68f3f-5" value="PK" style="shape=partialRectangle;fontStyle=1;top=0;left=0;bottom=0;html=1;fillColor=none;align=left;verticalAlign=middle;spacingLeft=4;spacingRight=4;whiteSpace=wrap;overflow=hidden;rotatable=0;points=[];portConstraint=eastwest;part=1;" parent="2e49270ec7c68f3f-4" vertex="1" connectable="0"><mxGeometry width="56" height="30" as="geometry"/></mxCell><mxCell id="81" value="user" style="shape=partialRectangle;top=0;left=0;right=0;bottom=0;html=1;align=left;verticalAlign=top;fillColor=none;spacingLeft=60;spacingRight=4;whiteSpace=wrap;overflow=hidden;rotatable=0;points=[[0,0.5],[1,0.5]];portConstraint=eastwest;dropTarget=0;" parent="2e49270ec7c68f3f-1" vertex="1"><mxGeometry y="56" width="199" height="34" as="geometry"/></mxCell><mxCell id="82" value="FK" style="shape=partialRectangle;top=0;left=0;bottom=0;html=1;fillColor=none;align=left;verticalAlign=top;spacingLeft=4;spacingRight=4;whiteSpace=wrap;overflow=hidden;rotatable=0;points=[];portConstraint=eastwest;part=1;" parent="81" vertex="1" connectable="0"><mxGeometry width="56" height="34" as="geometry"/></mxCell><mxCell id="2e49270ec7c68f3f-6" value="taskPorfolio&lt;div&gt;context&lt;/div&gt;" style="shape=partialRectangle;top=0;left=0;right=0;bottom=0;html=1;align=left;verticalAlign=top;fillColor=none;spacingLeft=60;spacingRight=4;whiteSpace=wrap;overflow=hidden;rotatable=0;points=[[0,0.5],[1,0.5]];portConstraint=eastwest;dropTarget=0;" parent="2e49270ec7c68f3f-1" vertex="1"><mxGeometry y="90" width="199" height="34" as="geometry"/></mxCell><mxCell id="2e49270ec7c68f3f-7" value="FK" style="shape=partialRectangle;top=0;left=0;bottom=0;html=1;fillColor=none;align=left;verticalAlign=top;spacingLeft=4;spacingRight=4;whiteSpace=wrap;overflow=hidden;rotatable=0;points=[];portConstraint=eastwest;part=1;" parent="2e49270ec7c68f3f-6" vertex="1" connectable="0"><mxGeometry width="56" height="34" as="geometry"/></mxCell><mxCell id="16" value="context" style="shape=partialRectangle;top=0;left=0;right=0;bottom=0;html=1;align=left;verticalAlign=top;fillColor=none;spacingLeft=60;spacingRight=4;whiteSpace=wrap;overflow=hidden;rotatable=0;points=[[0,0.5],[1,0.5]];portConstraint=eastwest;dropTarget=0;" parent="2e49270ec7c68f3f-1" vertex="1"><mxGeometry y="124" width="199" height="34" as="geometry"/></mxCell><mxCell id="17" value="FK" style="shape=partialRectangle;top=0;left=0;bottom=0;html=1;fillColor=none;align=left;verticalAlign=top;spacingLeft=4;spacingRight=4;whiteSpace=wrap;overflow=hidden;rotatable=0;points=[];portConstraint=eastwest;part=1;" parent="16" vertex="1" connectable="0"><mxGeometry width="56" height="34" as="geometry"/></mxCell><mxCell id="18" value="selfCompletionState" style="shape=partialRectangle;top=0;left=0;right=0;bottom=0;html=1;align=left;verticalAlign=top;fillColor=none;spacingLeft=60;spacingRight=4;whiteSpace=wrap;overflow=hidden;rotatable=0;points=[[0,0.5],[1,0.5]];portConstraint=eastwest;dropTarget=0;" parent="2e49270ec7c68f3f-1" vertex="1"><mxGeometry y="158" width="199" height="34" as="geometry"/></mxCell><mxCell id="19" value="FK" style="shape=partialRectangle;top=0;left=0;bottom=0;html=1;fillColor=none;align=left;verticalAlign=top;spacingLeft=4;spacingRight=4;whiteSpace=wrap;overflow=hidden;rotatable=0;points=[];portConstraint=eastwest;part=1;" parent="18" vertex="1" connectable="0"><mxGeometry width="56" height="34" as="geometry"/></mxCell><mxCell id="20" value="pointedCompletionState" style="shape=partialRectangle;top=0;left=0;right=0;bottom=0;html=1;align=left;verticalAlign=top;fillColor=none;spacingLeft=60;spacingRight=4;whiteSpace=wrap;overflow=hidden;rotatable=0;points=[[0,0.5],[1,0.5]];portConstraint=eastwest;dropTarget=0;" parent="2e49270ec7c68f3f-1" vertex="1"><mxGeometry y="192" width="199" height="34" as="geometry"/></mxCell><mxCell id="21" value="FK" style="shape=partialRectangle;top=0;left=0;bottom=0;html=1;fillColor=none;align=left;verticalAlign=top;spacingLeft=4;spacingRight=4;whiteSpace=wrap;overflow=hidden;rotatable=0;points=[];portConstraint=eastwest;part=1;" parent="20" vertex="1" connectable="0"><mxGeometry width="56" height="34" as="geometry"/></mxCell><mxCell id="22" value="InternalExecutionState" style="shape=partialRectangle;top=0;left=0;right=0;bottom=0;html=1;align=left;verticalAlign=top;fillColor=none;spacingLeft=60;spacingRight=4;whiteSpace=wrap;overflow=hidden;rotatable=0;points=[[0,0.5],[1,0.5]];portConstraint=eastwest;dropTarget=0;" parent="2e49270ec7c68f3f-1" vertex="1"><mxGeometry y="226" width="199" height="38" as="geometry"/></mxCell><mxCell id="23" value="FK" style="shape=partialRectangle;top=0;left=0;bottom=0;html=1;fillColor=none;align=left;verticalAlign=top;spacingLeft=4;spacingRight=4;whiteSpace=wrap;overflow=hidden;rotatable=0;points=[];portConstraint=eastwest;part=1;" parent="22" vertex="1" connectable="0"><mxGeometry width="56" height="38" as="geometry"/></mxCell><mxCell id="150" value="taskMetric" style="shape=partialRectangle;top=0;left=0;right=0;bottom=0;html=1;align=left;verticalAlign=top;fillColor=none;spacingLeft=60;spacingRight=4;whiteSpace=wrap;overflow=hidden;rotatable=0;points=[[0,0.5],[1,0.5]];portConstraint=eastwest;dropTarget=0;" vertex="1" parent="2e49270ec7c68f3f-1"><mxGeometry y="264" width="199" height="38" as="geometry"/></mxCell><mxCell id="151" value="FK" style="shape=partialRectangle;top=0;left=0;bottom=0;html=1;fillColor=none;align=left;verticalAlign=top;spacingLeft=4;spacingRight=4;whiteSpace=wrap;overflow=hidden;rotatable=0;points=[];portConstraint=eastwest;part=1;" vertex="1" connectable="0" parent="150"><mxGeometry width="56" height="38" as="geometry"/></mxCell><mxCell id="152" value="tasksBlockedByTheTask" style="shape=partialRectangle;top=0;left=0;right=0;bottom=0;html=1;align=left;verticalAlign=top;fillColor=none;spacingLeft=60;spacingRight=4;whiteSpace=wrap;overflow=hidden;rotatable=0;points=[[0,0.5],[1,0.5]];portConstraint=eastwest;dropTarget=0;" vertex="1" parent="2e49270ec7c68f3f-1"><mxGeometry y="302" width="199" height="38" as="geometry"/></mxCell><mxCell id="153" value="FK" style="shape=partialRectangle;top=0;left=0;bottom=0;html=1;fillColor=none;align=left;verticalAlign=top;spacingLeft=4;spacingRight=4;whiteSpace=wrap;overflow=hidden;rotatable=0;points=[];portConstraint=eastwest;part=1;" vertex="1" connectable="0" parent="152"><mxGeometry width="56" height="38" as="geometry"/></mxCell><mxCell id="259" value="tasksBlockingTheTask" style="shape=partialRectangle;top=0;left=0;right=0;bottom=0;html=1;align=left;verticalAlign=top;fillColor=none;spacingLeft=60;spacingRight=4;whiteSpace=wrap;overflow=hidden;rotatable=0;points=[[0,0.5],[1,0.5]];portConstraint=eastwest;dropTarget=0;" vertex="1" parent="2e49270ec7c68f3f-1"><mxGeometry y="340" width="199" height="38" as="geometry"/></mxCell><mxCell id="260" value="FK" style="shape=partialRectangle;top=0;left=0;bottom=0;html=1;fillColor=none;align=left;verticalAlign=top;spacingLeft=4;spacingRight=4;whiteSpace=wrap;overflow=hidden;rotatable=0;points=[];portConstraint=eastwest;part=1;" vertex="1" connectable="0" parent="259"><mxGeometry width="56" height="38" as="geometry"/></mxCell><mxCell id="261" value="externalTasks" style="shape=partialRectangle;top=0;left=0;right=0;bottom=0;html=1;align=left;verticalAlign=top;fillColor=none;spacingLeft=60;spacingRight=4;whiteSpace=wrap;overflow=hidden;rotatable=0;points=[[0,0.5],[1,0.5]];portConstraint=eastwest;dropTarget=0;" vertex="1" parent="2e49270ec7c68f3f-1"><mxGeometry y="378" width="199" height="38" as="geometry"/></mxCell><mxCell id="262" value="FK" style="shape=partialRectangle;top=0;left=0;bottom=0;html=1;fillColor=none;align=left;verticalAlign=top;spacingLeft=4;spacingRight=4;whiteSpace=wrap;overflow=hidden;rotatable=0;points=[];portConstraint=eastwest;part=1;" vertex="1" connectable="0" parent="261"><mxGeometry width="56" height="38" as="geometry"/></mxCell><mxCell id="263" value="internalTasks" style="shape=partialRectangle;top=0;left=0;right=0;bottom=0;html=1;align=left;verticalAlign=top;fillColor=none;spacingLeft=60;spacingRight=4;whiteSpace=wrap;overflow=hidden;rotatable=0;points=[[0,0.5],[1,0.5]];portConstraint=eastwest;dropTarget=0;" vertex="1" parent="2e49270ec7c68f3f-1"><mxGeometry y="416" width="199" height="38" as="geometry"/></mxCell><mxCell id="264" value="FK" style="shape=partialRectangle;top=0;left=0;bottom=0;html=1;fillColor=none;align=left;verticalAlign=top;spacingLeft=4;spacingRight=4;whiteSpace=wrap;overflow=hidden;rotatable=0;points=[];portConstraint=eastwest;part=1;" vertex="1" connectable="0" parent="263"><mxGeometry width="56" height="38" as="geometry"/></mxCell><mxCell id="256" style="edgeStyle=orthogonalEdgeStyle;rounded=0;html=1;exitX=1;exitY=0.5;startArrow=ERone;startFill=0;endArrow=ERoneToMany;endFill=0;jettySize=auto;orthogonalLoop=1;entryX=1;entryY=0.5;" edge="1" parent="2e49270ec7c68f3f-1" source="2e49270ec7c68f3f-4" target="261"><mxGeometry relative="1" as="geometry"><mxPoint x="319" y="409" as="targetPoint"/><Array as="points"><mxPoint x="319" y="41"/><mxPoint x="319" y="397"/></Array></mxGeometry></mxCell><mxCell id="265" style="edgeStyle=orthogonalEdgeStyle;rounded=0;html=1;exitX=1;exitY=0.5;startArrow=ERone;startFill=0;endArrow=ERoneToMany;endFill=0;jettySize=auto;orthogonalLoop=1;entryX=1;entryY=0.5;" edge="1" parent="2e49270ec7c68f3f-1" source="2e49270ec7c68f3f-4" target="263"><mxGeometry relative="1" as="geometry"><mxPoint x="359" y="429" as="targetPoint"/><Array as="points"><mxPoint x="359" y="41"/><mxPoint x="359" y="435"/></Array></mxGeometry></mxCell><mxCell id="2e49270ec7c68f3f-19" value="SelfCompletionState" style="swimlane;html=1;fontStyle=0;childLayout=stackLayout;horizontal=1;startSize=26;fillColor=#d5e8d4;horizontalStack=0;resizeParent=1;resizeLast=0;collapsible=1;marginBottom=0;swimlaneFillColor=#ffffff;align=center;rounded=0;shadow=0;comic=0;labelBackgroundColor=none;strokeColor=#82b366;strokeWidth=1;fontFamily=Verdana;fontSize=14;fontColor=#000000;" parent="1" vertex="1"><mxGeometry x="159" y="1161" width="160" height="79" as="geometry"/></mxCell><mxCell id="106" value="uniqueId" style="shape=partialRectangle;top=0;left=0;right=0;bottom=1;html=1;align=left;verticalAlign=middle;fillColor=none;spacingLeft=34;spacingRight=4;whiteSpace=wrap;overflow=hidden;rotatable=0;points=[[0,0.5],[1,0.5]];portConstraint=eastwest;dropTarget=0;fontStyle=5;" parent="2e49270ec7c68f3f-19" vertex="1"><mxGeometry y="26" width="160" height="30" as="geometry"/></mxCell><mxCell id="107" value="PK" style="shape=partialRectangle;top=0;left=0;bottom=0;html=1;fillColor=none;align=left;verticalAlign=middle;spacingLeft=4;spacingRight=4;whiteSpace=wrap;overflow=hidden;rotatable=0;points=[];portConstraint=eastwest;part=1;" parent="106" vertex="1" connectable="0"><mxGeometry width="30" height="30" as="geometry"/></mxCell><mxCell id="2e49270ec7c68f3f-30" value="PointedCompletionState" style="swimlane;html=1;fontStyle=0;childLayout=stackLayout;horizontal=1;startSize=26;fillColor=#d5e8d4;horizontalStack=0;resizeParent=1;resizeLast=0;collapsible=1;marginBottom=0;swimlaneFillColor=#ffffff;align=center;rounded=0;shadow=0;comic=0;labelBackgroundColor=none;strokeColor=#82b366;strokeWidth=1;fontFamily=Verdana;fontSize=14;fontColor=#000000;" parent="1" vertex="1"><mxGeometry x="760" y="1163" width="200" height="97" as="geometry"/></mxCell><mxCell id="2e49270ec7c68f3f-31" value="uniqueId" style="shape=partialRectangle;top=0;left=0;right=0;bottom=1;html=1;align=left;verticalAlign=middle;fillColor=none;spacingLeft=34;spacingRight=4;whiteSpace=wrap;overflow=hidden;rotatable=0;points=[[0,0.5],[1,0.5]];portConstraint=eastwest;dropTarget=0;fontStyle=5;" parent="2e49270ec7c68f3f-30" vertex="1"><mxGeometry y="26" width="200" height="34" as="geometry"/></mxCell><mxCell id="2e49270ec7c68f3f-32" value="PK" style="shape=partialRectangle;top=0;left=0;bottom=0;html=1;fillColor=none;align=left;verticalAlign=middle;spacingLeft=4;spacingRight=4;whiteSpace=wrap;overflow=hidden;rotatable=0;points=[];portConstraint=eastwest;part=1;" parent="2e49270ec7c68f3f-31" vertex="1" connectable="0"><mxGeometry width="30" height="34" as="geometry"/></mxCell><mxCell id="2e49270ec7c68f3f-41" value="TaskMetric" style="swimlane;html=1;fontStyle=0;childLayout=stackLayout;horizontal=1;startSize=26;fillColor=#f8cecc;horizontalStack=0;resizeParent=1;resizeLast=0;collapsible=1;marginBottom=0;swimlaneFillColor=#ffffff;align=center;rounded=0;shadow=0;comic=0;labelBackgroundColor=none;strokeColor=#b85450;strokeWidth=1;fontFamily=Verdana;fontSize=14;fontColor=#000000;" parent="1" vertex="1"><mxGeometry x="881" y="597" width="159" height="82" as="geometry"/></mxCell><mxCell id="2e49270ec7c68f3f-44" value="uniqueId" style="shape=partialRectangle;top=0;left=0;right=0;bottom=1;html=1;align=left;verticalAlign=middle;fillColor=none;spacingLeft=60;spacingRight=4;whiteSpace=wrap;overflow=hidden;rotatable=0;points=[[0,0.5],[1,0.5]];portConstraint=eastwest;dropTarget=0;fontStyle=5;" parent="2e49270ec7c68f3f-41" vertex="1"><mxGeometry y="26" width="159" height="30" as="geometry"/></mxCell><mxCell id="2e49270ec7c68f3f-45" value="PK" style="shape=partialRectangle;fontStyle=1;top=0;left=0;bottom=0;html=1;fillColor=none;align=left;verticalAlign=middle;spacingLeft=4;spacingRight=4;whiteSpace=wrap;overflow=hidden;rotatable=0;points=[];portConstraint=eastwest;part=1;" parent="2e49270ec7c68f3f-44" vertex="1" connectable="0"><mxGeometry width="52.477987421383645" height="30" as="geometry"/></mxCell><mxCell id="63" value="User" style="swimlane;html=1;fontStyle=0;childLayout=stackLayout;horizontal=1;startSize=26;fillColor=#dae8fc;horizontalStack=0;resizeParent=1;resizeLast=0;collapsible=1;marginBottom=0;swimlaneFillColor=#ffffff;align=center;rounded=0;shadow=0;comic=0;labelBackgroundColor=none;strokeColor=#6c8ebf;strokeWidth=1;fontFamily=Verdana;fontSize=14;fontColor=#000000;" parent="1" vertex="1"><mxGeometry x="160" y="82" width="160" height="160" as="geometry"/></mxCell><mxCell id="64" value="uniqueId" style="shape=partialRectangle;top=0;left=0;right=0;bottom=1;html=1;align=left;verticalAlign=middle;fillColor=none;spacingLeft=60;spacingRight=4;whiteSpace=wrap;overflow=hidden;rotatable=0;points=[[0,0.5],[1,0.5]];portConstraint=eastwest;dropTarget=0;fontStyle=5;" parent="63" vertex="1"><mxGeometry y="26" width="160" height="30" as="geometry"/></mxCell><mxCell id="65" value="PK" style="shape=partialRectangle;fontStyle=1;top=0;left=0;bottom=0;html=1;fillColor=none;align=left;verticalAlign=middle;spacingLeft=4;spacingRight=4;whiteSpace=wrap;overflow=hidden;rotatable=0;points=[];portConstraint=eastwest;part=1;" parent="64" vertex="1" connectable="0"><mxGeometry width="56" height="30" as="geometry"/></mxCell><mxCell id="79" value="role" style="shape=partialRectangle;top=0;left=0;right=0;bottom=0;html=1;align=left;verticalAlign=top;fillColor=none;spacingLeft=60;spacingRight=4;whiteSpace=wrap;overflow=hidden;rotatable=0;points=[[0,0.5],[1,0.5]];portConstraint=eastwest;dropTarget=0;" parent="63" vertex="1"><mxGeometry y="56" width="160" height="26" as="geometry"/></mxCell><mxCell id="80" value="FK" style="shape=partialRectangle;top=0;left=0;bottom=0;html=1;fillColor=none;align=left;verticalAlign=top;spacingLeft=4;spacingRight=4;whiteSpace=wrap;overflow=hidden;rotatable=0;points=[];portConstraint=eastwest;part=1;" parent="79" vertex="1" connectable="0"><mxGeometry width="56" height="26" as="geometry"/></mxCell><mxCell id="77" value="taskPortfolio" style="shape=partialRectangle;top=0;left=0;right=0;bottom=0;html=1;align=left;verticalAlign=top;fillColor=none;spacingLeft=60;spacingRight=4;whiteSpace=wrap;overflow=hidden;rotatable=0;points=[[0,0.5],[1,0.5]];portConstraint=eastwest;dropTarget=0;" parent="63" vertex="1"><mxGeometry y="82" width="160" height="26" as="geometry"/></mxCell><mxCell id="78" value="FK" style="shape=partialRectangle;top=0;left=0;bottom=0;html=1;fillColor=none;align=left;verticalAlign=top;spacingLeft=4;spacingRight=4;whiteSpace=wrap;overflow=hidden;rotatable=0;points=[];portConstraint=eastwest;part=1;" parent="77" vertex="1" connectable="0"><mxGeometry width="56" height="26" as="geometry"/></mxCell><mxCell id="116" value="context" style="shape=partialRectangle;top=0;left=0;right=0;bottom=0;html=1;align=left;verticalAlign=top;fillColor=none;spacingLeft=60;spacingRight=4;whiteSpace=wrap;overflow=hidden;rotatable=0;points=[[0,0.5],[1,0.5]];portConstraint=eastwest;dropTarget=0;" parent="63" vertex="1"><mxGeometry y="108" width="160" height="26" as="geometry"/></mxCell><mxCell id="117" value="FK" style="shape=partialRectangle;top=0;left=0;bottom=0;html=1;fillColor=none;align=left;verticalAlign=top;spacingLeft=4;spacingRight=4;whiteSpace=wrap;overflow=hidden;rotatable=0;points=[];portConstraint=eastwest;part=1;" parent="116" vertex="1" connectable="0"><mxGeometry width="56" height="26" as="geometry"/></mxCell><mxCell id="98" value="metric" style="shape=partialRectangle;top=0;left=0;right=0;bottom=0;html=1;align=left;verticalAlign=top;fillColor=none;spacingLeft=60;spacingRight=4;whiteSpace=wrap;overflow=hidden;rotatable=0;points=[[0,0.5],[1,0.5]];portConstraint=eastwest;dropTarget=0;" parent="63" vertex="1"><mxGeometry y="134" width="160" height="26" as="geometry"/></mxCell><mxCell id="99" value="FK" style="shape=partialRectangle;top=0;left=0;bottom=0;html=1;fillColor=none;align=left;verticalAlign=top;spacingLeft=4;spacingRight=4;whiteSpace=wrap;overflow=hidden;rotatable=0;points=[];portConstraint=eastwest;part=1;" parent="98" vertex="1" connectable="0"><mxGeometry width="56" height="26" as="geometry"/></mxCell><mxCell id="147" style="edgeStyle=orthogonalEdgeStyle;rounded=0;html=1;exitX=1;exitY=0.5;entryX=0;entryY=0.5;startArrow=ERone;startFill=0;endArrow=ERoneToMany;endFill=0;jettySize=auto;orthogonalLoop=1;" edge="1" parent="1" source="88" target="141"><mxGeometry relative="1" as="geometry"><Array as="points"><mxPoint x="640" y="200"/><mxPoint x="640" y="146"/></Array></mxGeometry></mxCell><mxCell id="88" value="Role" style="swimlane;html=1;fontStyle=0;childLayout=stackLayout;horizontal=1;startSize=26;fillColor=#dae8fc;horizontalStack=0;resizeParent=1;resizeLast=0;collapsible=1;marginBottom=0;swimlaneFillColor=#ffffff;align=center;rounded=0;shadow=0;comic=0;labelBackgroundColor=none;strokeColor=#6c8ebf;strokeWidth=1;fontFamily=Verdana;fontSize=14;fontColor=#000000;" parent="1" vertex="1"><mxGeometry x="440" y="156" width="160" height="86" as="geometry"/></mxCell><mxCell id="89" value="uniqueId" style="shape=partialRectangle;top=0;left=0;right=0;bottom=1;html=1;align=left;verticalAlign=middle;fillColor=none;spacingLeft=60;spacingRight=4;whiteSpace=wrap;overflow=hidden;rotatable=0;points=[[0,0.5],[1,0.5]];portConstraint=eastwest;dropTarget=0;fontStyle=5;" parent="88" vertex="1"><mxGeometry y="26" width="160" height="30" as="geometry"/></mxCell><mxCell id="90" value="PK" style="shape=partialRectangle;fontStyle=1;top=0;left=0;bottom=0;html=1;fillColor=none;align=left;verticalAlign=middle;spacingLeft=4;spacingRight=4;whiteSpace=wrap;overflow=hidden;rotatable=0;points=[];portConstraint=eastwest;part=1;" parent="89" vertex="1" connectable="0"><mxGeometry width="56" height="30" as="geometry"/></mxCell><mxCell id="2e49270ec7c68f3f-48" value="InternalExecutionState" style="swimlane;html=1;fontStyle=0;childLayout=stackLayout;horizontal=1;startSize=26;fillColor=#d5e8d4;horizontalStack=0;resizeParent=1;resizeLast=0;collapsible=1;marginBottom=0;swimlaneFillColor=#ffffff;align=center;rounded=0;shadow=0;comic=0;labelBackgroundColor=none;strokeColor=#82b366;strokeWidth=1;fontFamily=Verdana;fontSize=14;fontColor=#000000;" parent="1" vertex="1"><mxGeometry x="159" y="1362" width="200" height="80" as="geometry"/></mxCell><mxCell id="2e49270ec7c68f3f-51" value="uniqueId" style="shape=partialRectangle;top=0;left=0;right=0;bottom=1;html=1;align=left;verticalAlign=middle;fillColor=none;spacingLeft=60;spacingRight=4;whiteSpace=wrap;overflow=hidden;rotatable=0;points=[[0,0.5],[1,0.5]];portConstraint=eastwest;dropTarget=0;fontStyle=5;" parent="2e49270ec7c68f3f-48" vertex="1"><mxGeometry y="26" width="200" height="30" as="geometry"/></mxCell><mxCell id="2e49270ec7c68f3f-52" value="PK" style="shape=partialRectangle;fontStyle=1;top=0;left=0;bottom=0;html=1;fillColor=none;align=left;verticalAlign=middle;spacingLeft=4;spacingRight=4;whiteSpace=wrap;overflow=hidden;rotatable=0;points=[];portConstraint=eastwest;part=1;" parent="2e49270ec7c68f3f-51" vertex="1" connectable="0"><mxGeometry width="56" height="30" as="geometry"/></mxCell><mxCell id="2e49270ec7c68f3f-80" value="TaskPortfolio" style="swimlane;html=1;fontStyle=0;childLayout=stackLayout;horizontal=1;startSize=26;fillColor=#f8cecc;horizontalStack=0;resizeParent=1;resizeLast=0;collapsible=1;marginBottom=0;swimlaneFillColor=#ffffff;align=center;rounded=0;shadow=0;comic=0;labelBackgroundColor=none;strokeColor=#b85450;strokeWidth=1;fontFamily=Verdana;fontSize=14;fontColor=#000000;" parent="1" vertex="1"><mxGeometry x="160" y="401" width="160" height="79" as="geometry"/></mxCell><mxCell id="2e49270ec7c68f3f-81" value="uniqueId" style="shape=partialRectangle;top=0;left=0;right=0;bottom=1;html=1;align=left;verticalAlign=middle;fillColor=none;spacingLeft=34;spacingRight=4;whiteSpace=wrap;overflow=hidden;rotatable=0;points=[[0,0.5],[1,0.5]];portConstraint=eastwest;dropTarget=0;fontStyle=5;" parent="2e49270ec7c68f3f-80" vertex="1"><mxGeometry y="26" width="160" height="30" as="geometry"/></mxCell><mxCell id="2e49270ec7c68f3f-82" value="PK" style="shape=partialRectangle;top=0;left=0;bottom=0;html=1;fillColor=none;align=left;verticalAlign=middle;spacingLeft=4;spacingRight=4;whiteSpace=wrap;overflow=hidden;rotatable=0;points=[];portConstraint=eastwest;part=1;" parent="2e49270ec7c68f3f-81" vertex="1" connectable="0"><mxGeometry width="30" height="30" as="geometry"/></mxCell><mxCell id="2" value="TaskContext" style="swimlane;html=1;fontStyle=0;childLayout=stackLayout;horizontal=1;startSize=26;fillColor=#f8cecc;horizontalStack=0;resizeParent=1;resizeLast=0;collapsible=1;marginBottom=0;swimlaneFillColor=#ffffff;align=center;rounded=0;shadow=0;comic=0;labelBackgroundColor=none;strokeColor=#b85450;strokeWidth=1;fontFamily=Verdana;fontSize=14;fontColor=#000000;" parent="1" vertex="1"><mxGeometry x="1201" y="401" width="160" height="124" as="geometry"/></mxCell><mxCell id="242" style="edgeStyle=orthogonalEdgeStyle;rounded=0;html=1;exitX=0;exitY=0.5;entryX=0;entryY=0.5;startArrow=ERone;startFill=0;endArrow=ERoneToMany;endFill=0;jettySize=auto;orthogonalLoop=1;" edge="1" parent="2" source="209" target="238"><mxGeometry relative="1" as="geometry"><Array as="points"><mxPoint x="-40" y="41"/><mxPoint x="-40" y="73"/></Array></mxGeometry></mxCell><mxCell id="209" value="iniqueid" style="shape=partialRectangle;top=0;left=0;right=0;bottom=1;html=1;align=left;verticalAlign=middle;fillColor=none;spacingLeft=60;spacingRight=4;whiteSpace=wrap;overflow=hidden;rotatable=0;points=[[0,0.5],[1,0.5]];portConstraint=eastwest;dropTarget=0;fontStyle=5;" vertex="1" parent="2"><mxGeometry y="26" width="160" height="30" as="geometry"/></mxCell><mxCell id="210" value="PK" style="shape=partialRectangle;fontStyle=1;top=0;left=0;bottom=0;html=1;fillColor=none;align=left;verticalAlign=middle;spacingLeft=4;spacingRight=4;whiteSpace=wrap;overflow=hidden;rotatable=0;points=[];portConstraint=eastwest;part=1;" vertex="1" connectable="0" parent="209"><mxGeometry width="56" height="30" as="geometry"/></mxCell><mxCell id="238" value="externalContext" style="shape=partialRectangle;top=0;left=0;right=0;bottom=0;html=1;align=left;verticalAlign=top;fillColor=none;spacingLeft=60;spacingRight=4;whiteSpace=wrap;overflow=hidden;rotatable=0;points=[[0,0.5],[1,0.5]];portConstraint=eastwest;dropTarget=0;" vertex="1" parent="2"><mxGeometry y="56" width="160" height="34" as="geometry"/></mxCell><mxCell id="239" value="FK" style="shape=partialRectangle;top=0;left=0;bottom=0;html=1;fillColor=none;align=left;verticalAlign=top;spacingLeft=4;spacingRight=4;whiteSpace=wrap;overflow=hidden;rotatable=0;points=[];portConstraint=eastwest;part=1;" vertex="1" connectable="0" parent="238"><mxGeometry width="56" height="34" as="geometry"/></mxCell><mxCell id="240" value="internalContext" style="shape=partialRectangle;top=0;left=0;right=0;bottom=0;html=1;align=left;verticalAlign=top;fillColor=none;spacingLeft=60;spacingRight=4;whiteSpace=wrap;overflow=hidden;rotatable=0;points=[[0,0.5],[1,0.5]];portConstraint=eastwest;dropTarget=0;" vertex="1" parent="2"><mxGeometry y="90" width="160" height="34" as="geometry"/></mxCell><mxCell id="241" value="FK" style="shape=partialRectangle;top=0;left=0;bottom=0;html=1;fillColor=none;align=left;verticalAlign=top;spacingLeft=4;spacingRight=4;whiteSpace=wrap;overflow=hidden;rotatable=0;points=[];portConstraint=eastwest;part=1;" vertex="1" connectable="0" parent="240"><mxGeometry width="56" height="34" as="geometry"/></mxCell><mxCell id="243" style="edgeStyle=orthogonalEdgeStyle;rounded=0;html=1;exitX=0;exitY=0.5;startArrow=ERone;startFill=0;endArrow=ERoneToMany;endFill=0;jettySize=auto;orthogonalLoop=1;entryX=0;entryY=0.5;" edge="1" parent="2" source="209" target="240"><mxGeometry relative="1" as="geometry"><mxPoint x="-80" y="41" as="targetPoint"/><Array as="points"><mxPoint x="-80" y="41"/><mxPoint x="-80" y="107"/></Array></mxGeometry></mxCell><mxCell id="9" style="edgeStyle=orthogonalEdgeStyle;rounded=0;html=1;exitX=1;exitY=0.5;startArrow=ERone;startFill=0;endArrow=ERoneToMany;endFill=0;jettySize=auto;orthogonalLoop=1;entryX=0;entryY=0.5;" parent="1" source="2e49270ec7c68f3f-81" target="2e49270ec7c68f3f-6" edge="1"><mxGeometry relative="1" as="geometry"><mxPoint x="270" y="516" as="targetPoint"/><Array as="points"><mxPoint x="360" y="442"/><mxPoint x="360" y="508"/></Array></mxGeometry></mxCell><mxCell id="24" style="edgeStyle=orthogonalEdgeStyle;rounded=0;html=1;exitX=1;exitY=0.5;startArrow=ERone;startFill=0;endArrow=ERoneToMany;endFill=0;jettySize=auto;orthogonalLoop=1;entryX=0;entryY=0.5;" parent="1" source="2e49270ec7c68f3f-4" target="205" edge="1"><mxGeometry relative="1" as="geometry"><mxPoint x="760" y="490" as="targetPoint"/><Array as="points"><mxPoint x="680" y="442"/><mxPoint x="680" y="400"/><mxPoint x="840" y="400"/><mxPoint x="840" y="444"/></Array></mxGeometry></mxCell><mxCell id="26" style="edgeStyle=orthogonalEdgeStyle;rounded=0;html=1;startArrow=ERoneToMany;startFill=0;endArrow=ERone;endFill=0;jettySize=auto;orthogonalLoop=1;exitX=0;exitY=0.5;entryX=0;entryY=0.5;" parent="1" source="18" target="106" edge="1"><mxGeometry relative="1" as="geometry"><mxPoint x="270" y="620" as="sourcePoint"/><mxPoint x="160" y="1082" as="targetPoint"/><Array as="points"><mxPoint x="120" y="576"/><mxPoint x="120" y="1202"/></Array></mxGeometry></mxCell><mxCell id="46" style="edgeStyle=orthogonalEdgeStyle;rounded=0;html=1;exitX=0;exitY=0.5;startArrow=ERoneToMany;startFill=0;endArrow=ERone;endFill=0;jettySize=auto;orthogonalLoop=1;entryX=0;entryY=0.5;" parent="1" source="22" edge="1" target="2e49270ec7c68f3f-51"><mxGeometry relative="1" as="geometry"><mxPoint x="440" y="1280" as="targetPoint"/><Array as="points"><mxPoint x="80" y="646"/><mxPoint x="80" y="1404"/></Array></mxGeometry></mxCell><mxCell id="84" style="edgeStyle=orthogonalEdgeStyle;rounded=0;html=1;startArrow=ERoneToMany;startFill=0;endArrow=ERone;endFill=0;jettySize=auto;orthogonalLoop=1;entryX=0;entryY=0.5;exitX=0;exitY=0.5;" parent="1" source="2e49270ec7c68f3f-4" target="64" edge="1"><mxGeometry relative="1" as="geometry"><mxPoint x="730" y="280" as="targetPoint"/><Array as="points"><mxPoint x="400" y="442"/><mxPoint x="400" y="520"/><mxPoint x="80" y="520"/><mxPoint x="80" y="124"/></Array><mxPoint x="442" y="480" as="sourcePoint"/></mxGeometry></mxCell><mxCell id="86" style="edgeStyle=orthogonalEdgeStyle;rounded=0;html=1;exitX=0;exitY=0.5;startArrow=ERoneToMany;startFill=0;endArrow=ERone;endFill=0;jettySize=auto;orthogonalLoop=1;entryX=0;entryY=0.5;" parent="1" source="2e49270ec7c68f3f-81" target="77" edge="1"><mxGeometry relative="1" as="geometry"><mxPoint x="30" y="110" as="targetPoint"/><Array as="points"><mxPoint x="120" y="442"/><mxPoint x="120" y="178"/></Array></mxGeometry></mxCell><mxCell id="100" style="edgeStyle=orthogonalEdgeStyle;rounded=0;html=1;exitX=0.5;exitY=1;entryX=0.5;entryY=1;startArrow=ERoneToMany;startFill=0;endArrow=ERoneToMany;endFill=0;jettySize=auto;orthogonalLoop=1;" parent="1" source="2e49270ec7c68f3f-30" target="2e49270ec7c68f3f-30" edge="1"><mxGeometry relative="1" as="geometry"/></mxCell><mxCell id="115" style="edgeStyle=orthogonalEdgeStyle;rounded=0;html=1;startArrow=ERone;startFill=0;endArrow=ERoneToMany;endFill=0;jettySize=auto;orthogonalLoop=1;exitX=1;exitY=0.5;entryX=1;entryY=0.5;" parent="1" edge="1" target="209"><mxGeometry relative="1" as="geometry"><mxPoint x="320" y="203" as="sourcePoint"/><mxPoint x="1316" y="402" as="targetPoint"/><Array as="points"><mxPoint x="400" y="204"/><mxPoint x="400" y="280"/><mxPoint x="1400" y="280"/><mxPoint x="1400" y="442"/></Array></mxGeometry></mxCell><mxCell id="119" value="Users context" style="shape=umlFrame;whiteSpace=wrap;html=1;fillColor=#dae8fc;strokeColor=#6c8ebf;labelBackgroundColor=none;shadow=0;gradientColor=none;" parent="1" vertex="1"><mxGeometry x="40" y="41" width="960" height="279" as="geometry"/></mxCell><mxCell id="125" style="edgeStyle=orthogonalEdgeStyle;rounded=0;html=1;exitX=0;exitY=0.5;entryX=1;entryY=0.5;startArrow=ERoneToMany;startFill=0;endArrow=ERone;endFill=0;jettySize=auto;orthogonalLoop=1;" parent="1" target="79" edge="1"><mxGeometry relative="1" as="geometry"><Array as="points"><mxPoint x="680" y="122"/><mxPoint x="680" y="80"/><mxPoint x="360" y="80"/><mxPoint x="360" y="152"/></Array><mxPoint x="720" y="122" as="sourcePoint"/></mxGeometry></mxCell><mxCell id="126" value="Tasks context" style="shape=umlFrame;whiteSpace=wrap;html=1;fillColor=#f8cecc;strokeColor=#b85450;" parent="1" vertex="1"><mxGeometry x="40" y="361" width="1440" height="719" as="geometry"/></mxCell><mxCell id="132" style="edgeStyle=orthogonalEdgeStyle;rounded=0;html=1;startArrow=ERoneToMany;startFill=0;endArrow=ERone;endFill=0;jettySize=auto;orthogonalLoop=1;entryX=0;entryY=0.5;exitX=0;exitY=0.5;" parent="1" source="226" target="20" edge="1"><mxGeometry relative="1" as="geometry"><mxPoint x="290" y="620" as="targetPoint"/><Array as="points"><mxPoint x="360" y="1238"/><mxPoint x="360" y="1040"/><mxPoint x="160" y="1040"/><mxPoint x="160" y="610"/></Array><mxPoint x="442" y="1110" as="sourcePoint"/></mxGeometry></mxCell><mxCell id="133" value="States&lt;div&gt;context&lt;/div&gt;" style="shape=umlFrame;whiteSpace=wrap;html=1;fillColor=#d5e8d4;strokeColor=#82b366;" parent="1" vertex="1"><mxGeometry x="38" y="1121" width="1042" height="360" as="geometry"/></mxCell><mxCell id="134" value="Note for the TaskMetric:&amp;nbsp;&lt;div&gt;on the second iteration will be implemented&amp;nbsp;&lt;span&gt;one-to-one dependency.&lt;/span&gt;&lt;/div&gt;" style="shape=note;whiteSpace=wrap;html=1;size=14;verticalAlign=top;align=left;spacingTop=-6;shadow=0;labelBackgroundColor=none;fillColor=#f8cecc;strokeColor=#b85450;" vertex="1" parent="1"><mxGeometry x="881" y="693" width="159" height="64" as="geometry"/></mxCell><mxCell id="135" value="Note for the User:&amp;nbsp;&lt;div&gt;on the second iteration won't be the relation between TaskMetric and User&lt;span&gt;.&lt;/span&gt;&lt;/div&gt;" style="shape=note;whiteSpace=wrap;html=1;size=14;verticalAlign=top;align=left;spacingTop=-6;shadow=0;labelBackgroundColor=none;fillColor=#dae8fc;strokeColor=#6c8ebf;" vertex="1" parent="1"><mxGeometry x="417" y="87" width="159" height="64" as="geometry"/></mxCell><mxCell id="136" value="User_Role" style="swimlane;html=1;fontStyle=0;childLayout=stackLayout;horizontal=1;startSize=26;fillColor=#dae8fc;horizontalStack=0;resizeParent=1;resizeLast=0;collapsible=1;marginBottom=0;swimlaneFillColor=#ffffff;align=center;rounded=0;shadow=0;comic=0;labelBackgroundColor=none;strokeColor=#6c8ebf;strokeWidth=1;fontFamily=Verdana;fontSize=14;fontColor=#000000;" vertex="1" parent="1"><mxGeometry x="720" y="81" width="160" height="79" as="geometry"/></mxCell><mxCell id="139" value="user" style="shape=partialRectangle;top=0;left=0;right=0;bottom=0;html=1;align=left;verticalAlign=top;fillColor=none;spacingLeft=60;spacingRight=4;whiteSpace=wrap;overflow=hidden;rotatable=0;points=[[0,0.5],[1,0.5]];portConstraint=eastwest;dropTarget=0;" vertex="1" parent="136"><mxGeometry y="26" width="160" height="26" as="geometry"/></mxCell><mxCell id="140" value="FK" style="shape=partialRectangle;top=0;left=0;bottom=0;html=1;fillColor=none;align=left;verticalAlign=top;spacingLeft=4;spacingRight=4;whiteSpace=wrap;overflow=hidden;rotatable=0;points=[];portConstraint=eastwest;part=1;" vertex="1" connectable="0" parent="139"><mxGeometry width="56" height="26" as="geometry"/></mxCell><mxCell id="141" value="role" style="shape=partialRectangle;top=0;left=0;right=0;bottom=0;html=1;align=left;verticalAlign=top;fillColor=none;spacingLeft=60;spacingRight=4;whiteSpace=wrap;overflow=hidden;rotatable=0;points=[[0,0.5],[1,0.5]];portConstraint=eastwest;dropTarget=0;" vertex="1" parent="136"><mxGeometry y="52" width="160" height="26" as="geometry"/></mxCell><mxCell id="142" value="FK" style="shape=partialRectangle;top=0;left=0;bottom=0;html=1;fillColor=none;align=left;verticalAlign=top;spacingLeft=4;spacingRight=4;whiteSpace=wrap;overflow=hidden;rotatable=0;points=[];portConstraint=eastwest;part=1;" vertex="1" connectable="0" parent="141"><mxGeometry width="56" height="26" as="geometry"/></mxCell><mxCell id="160" style="edgeStyle=orthogonalEdgeStyle;rounded=0;html=1;exitX=0;exitY=0.5;startArrow=ERone;startFill=0;endArrow=ERoneToMany;endFill=0;jettySize=auto;orthogonalLoop=1;entryX=0;entryY=0.5;" edge="1" parent="1" source="152" target="187"><mxGeometry relative="1" as="geometry"><mxPoint x="786" y="680" as="targetPoint"/><Array as="points"><mxPoint x="200" y="722"/><mxPoint x="200" y="1016"/></Array></mxGeometry></mxCell><mxCell id="164" style="edgeStyle=orthogonalEdgeStyle;rounded=0;html=1;exitX=0;exitY=0.5;startArrow=ERone;startFill=0;endArrow=ERoneToMany;endFill=0;jettySize=auto;orthogonalLoop=1;entryX=0;entryY=0.5;" edge="1" parent="1" source="259" target="229"><mxGeometry relative="1" as="geometry"><mxPoint x="442" y="772" as="sourcePoint"/><mxPoint x="770" y="844" as="targetPoint"/><Array as="points"><mxPoint x="240" y="760"/><mxPoint x="240" y="968"/></Array></mxGeometry></mxCell><mxCell id="180" value="TaskBlocked_TaskBlocking" style="swimlane;html=1;fontStyle=0;childLayout=stackLayout;horizontal=1;startSize=26;fillColor=#f8cecc;horizontalStack=0;resizeParent=1;resizeLast=0;collapsible=1;marginBottom=0;swimlaneFillColor=#ffffff;align=center;rounded=0;shadow=0;comic=0;labelBackgroundColor=none;strokeColor=#b85450;strokeWidth=1;fontFamily=Verdana;fontSize=14;fontColor=#000000;" vertex="1" parent="1"><mxGeometry x="1162" y="920" width="199" height="120" as="geometry"/></mxCell><mxCell id="229" value="taskBlockingTheTask" style="shape=partialRectangle;top=0;left=0;right=0;bottom=0;html=1;align=left;verticalAlign=top;fillColor=none;spacingLeft=60;spacingRight=4;whiteSpace=wrap;overflow=hidden;rotatable=0;points=[[0,0.5],[1,0.5]];portConstraint=eastwest;dropTarget=0;" vertex="1" parent="180"><mxGeometry y="26" width="199" height="44" as="geometry"/></mxCell><mxCell id="230" value="FK" style="shape=partialRectangle;top=0;left=0;bottom=0;html=1;fillColor=none;align=left;verticalAlign=top;spacingLeft=4;spacingRight=4;whiteSpace=wrap;overflow=hidden;rotatable=0;points=[];portConstraint=eastwest;part=1;" vertex="1" connectable="0" parent="229"><mxGeometry width="56" height="44" as="geometry"/></mxCell><mxCell id="187" value="taskBlockedByTheTask" style="shape=partialRectangle;top=0;left=0;right=0;bottom=0;html=1;align=left;verticalAlign=top;fillColor=none;spacingLeft=60;spacingRight=4;whiteSpace=wrap;overflow=hidden;rotatable=0;points=[[0,0.5],[1,0.5]];portConstraint=eastwest;dropTarget=0;" vertex="1" parent="180"><mxGeometry y="70" width="199" height="50" as="geometry"/></mxCell><mxCell id="188" value="FK" style="shape=partialRectangle;top=0;left=0;bottom=0;html=1;fillColor=none;align=left;verticalAlign=top;spacingLeft=4;spacingRight=4;whiteSpace=wrap;overflow=hidden;rotatable=0;points=[];portConstraint=eastwest;part=1;" vertex="1" connectable="0" parent="187"><mxGeometry width="56" height="50" as="geometry"/></mxCell><mxCell id="204" value="Task_TaskContext" style="swimlane;html=1;fontStyle=0;childLayout=stackLayout;horizontal=1;startSize=26;fillColor=#f8cecc;horizontalStack=0;resizeParent=1;resizeLast=0;collapsible=1;marginBottom=0;swimlaneFillColor=#ffffff;align=center;rounded=0;shadow=0;comic=0;labelBackgroundColor=none;strokeColor=#b85450;strokeWidth=1;fontFamily=Verdana;fontSize=14;fontColor=#000000;" vertex="1" parent="1"><mxGeometry x="882" y="401" width="159" height="95" as="geometry"/></mxCell><mxCell id="205" value="task&lt;br&gt;" style="shape=partialRectangle;top=0;left=0;right=0;bottom=0;html=1;align=left;verticalAlign=top;fillColor=none;spacingLeft=60;spacingRight=4;whiteSpace=wrap;overflow=hidden;rotatable=0;points=[[0,0.5],[1,0.5]];portConstraint=eastwest;dropTarget=0;" vertex="1" parent="204"><mxGeometry y="26" width="159" height="34" as="geometry"/></mxCell><mxCell id="206" value="FK" style="shape=partialRectangle;top=0;left=0;bottom=0;html=1;fillColor=none;align=left;verticalAlign=top;spacingLeft=4;spacingRight=4;whiteSpace=wrap;overflow=hidden;rotatable=0;points=[];portConstraint=eastwest;part=1;" vertex="1" connectable="0" parent="205"><mxGeometry width="56" height="34" as="geometry"/></mxCell><mxCell id="207" value="context" style="shape=partialRectangle;top=0;left=0;right=0;bottom=0;html=1;align=left;verticalAlign=top;fillColor=none;spacingLeft=60;spacingRight=4;whiteSpace=wrap;overflow=hidden;rotatable=0;points=[[0,0.5],[1,0.5]];portConstraint=eastwest;dropTarget=0;" vertex="1" parent="204"><mxGeometry y="60" width="159" height="34" as="geometry"/></mxCell><mxCell id="208" value="FK" style="shape=partialRectangle;top=0;left=0;bottom=0;html=1;fillColor=none;align=left;verticalAlign=top;spacingLeft=4;spacingRight=4;whiteSpace=wrap;overflow=hidden;rotatable=0;points=[];portConstraint=eastwest;part=1;" vertex="1" connectable="0" parent="207"><mxGeometry width="56" height="34" as="geometry"/></mxCell><mxCell id="211" style="edgeStyle=orthogonalEdgeStyle;rounded=0;html=1;exitX=0;exitY=0.5;entryX=0;entryY=0.5;startArrow=ERone;startFill=0;endArrow=ERoneToMany;endFill=0;jettySize=auto;orthogonalLoop=1;" edge="1" parent="204" source="207" target="207"><mxGeometry relative="1" as="geometry"/></mxCell><mxCell id="212" style="edgeStyle=orthogonalEdgeStyle;rounded=0;html=1;exitX=0;exitY=0.5;entryX=1;entryY=0.5;startArrow=ERone;startFill=0;endArrow=ERoneToMany;endFill=0;jettySize=auto;orthogonalLoop=1;" edge="1" parent="1" source="209" target="207"><mxGeometry relative="1" as="geometry"><Array as="points"><mxPoint x="1161" y="442"/><mxPoint x="1161" y="400"/><mxPoint x="1081" y="400"/><mxPoint x="1081" y="478"/></Array></mxGeometry></mxCell><mxCell id="216" style="edgeStyle=orthogonalEdgeStyle;rounded=0;html=1;exitX=1;exitY=0.5;entryX=0;entryY=0.5;startArrow=ERone;startFill=0;endArrow=ERone;endFill=0;jettySize=auto;orthogonalLoop=1;" edge="1" parent="1" source="150" target="2e49270ec7c68f3f-44"><mxGeometry relative="1" as="geometry"><Array as="points"><mxPoint x="840" y="684"/><mxPoint x="840" y="638"/></Array></mxGeometry></mxCell><mxCell id="223" value="PointedState_Task" style="swimlane;html=1;fontStyle=0;childLayout=stackLayout;horizontal=1;startSize=26;fillColor=#d5e8d4;horizontalStack=0;resizeParent=1;resizeLast=0;collapsible=1;marginBottom=0;swimlaneFillColor=#ffffff;align=center;rounded=0;shadow=0;comic=0;labelBackgroundColor=none;strokeColor=#82b366;strokeWidth=1;fontFamily=Verdana;fontSize=14;fontColor=#000000;" vertex="1" parent="1"><mxGeometry x="440" y="1161" width="198" height="95" as="geometry"/></mxCell><mxCell id="224" value="pointedState" style="shape=partialRectangle;top=0;left=0;right=0;bottom=0;html=1;align=left;verticalAlign=top;fillColor=none;spacingLeft=60;spacingRight=4;whiteSpace=wrap;overflow=hidden;rotatable=0;points=[[0,0.5],[1,0.5]];portConstraint=eastwest;dropTarget=0;" vertex="1" parent="223"><mxGeometry y="26" width="198" height="34" as="geometry"/></mxCell><mxCell id="225" value="FK" style="shape=partialRectangle;top=0;left=0;bottom=0;html=1;fillColor=none;align=left;verticalAlign=top;spacingLeft=4;spacingRight=4;whiteSpace=wrap;overflow=hidden;rotatable=0;points=[];portConstraint=eastwest;part=1;" vertex="1" connectable="0" parent="224"><mxGeometry width="56" height="34" as="geometry"/></mxCell><mxCell id="226" value="task" style="shape=partialRectangle;top=0;left=0;right=0;bottom=0;html=1;align=left;verticalAlign=top;fillColor=none;spacingLeft=60;spacingRight=4;whiteSpace=wrap;overflow=hidden;rotatable=0;points=[[0,0.5],[1,0.5]];portConstraint=eastwest;dropTarget=0;" vertex="1" parent="223"><mxGeometry y="60" width="198" height="34" as="geometry"/></mxCell><mxCell id="227" value="FK" style="shape=partialRectangle;top=0;left=0;bottom=0;html=1;fillColor=none;align=left;verticalAlign=top;spacingLeft=4;spacingRight=4;whiteSpace=wrap;overflow=hidden;rotatable=0;points=[];portConstraint=eastwest;part=1;" vertex="1" connectable="0" parent="226"><mxGeometry width="56" height="34" as="geometry"/></mxCell><mxCell id="228" style="edgeStyle=orthogonalEdgeStyle;rounded=0;html=1;entryX=1;entryY=0.5;startArrow=ERone;startFill=0;endArrow=ERoneToMany;endFill=0;jettySize=auto;orthogonalLoop=1;" edge="1" parent="1" target="224"><mxGeometry relative="1" as="geometry"><mxPoint x="760" y="1204" as="sourcePoint"/><Array as="points"><mxPoint x="740" y="1204"/><mxPoint x="740" y="1204"/></Array></mxGeometry></mxCell><mxCell id="244" value="External_InternalContext" style="swimlane;html=1;fontStyle=0;childLayout=stackLayout;horizontal=1;startSize=26;fillColor=#f8cecc;horizontalStack=0;resizeParent=1;resizeLast=0;collapsible=1;marginBottom=0;swimlaneFillColor=#ffffff;align=center;rounded=0;shadow=0;comic=0;labelBackgroundColor=none;strokeColor=#b85450;strokeWidth=1;fontFamily=Verdana;fontSize=14;fontColor=#000000;" vertex="1" parent="1"><mxGeometry x="1161" y="641" width="200" height="124" as="geometry"/></mxCell><mxCell id="246" value="iniqueid" style="shape=partialRectangle;top=0;left=0;right=0;bottom=1;html=1;align=left;verticalAlign=middle;fillColor=none;spacingLeft=60;spacingRight=4;whiteSpace=wrap;overflow=hidden;rotatable=0;points=[[0,0.5],[1,0.5]];portConstraint=eastwest;dropTarget=0;fontStyle=5;" vertex="1" parent="244"><mxGeometry y="26" width="200" height="30" as="geometry"/></mxCell><mxCell id="247" value="PK" style="shape=partialRectangle;fontStyle=1;top=0;left=0;bottom=0;html=1;fillColor=none;align=left;verticalAlign=middle;spacingLeft=4;spacingRight=4;whiteSpace=wrap;overflow=hidden;rotatable=0;points=[];portConstraint=eastwest;part=1;" vertex="1" connectable="0" parent="246"><mxGeometry width="56" height="30" as="geometry"/></mxCell><mxCell id="248" value="externalContext" style="shape=partialRectangle;top=0;left=0;right=0;bottom=0;html=1;align=left;verticalAlign=top;fillColor=none;spacingLeft=60;spacingRight=4;whiteSpace=wrap;overflow=hidden;rotatable=0;points=[[0,0.5],[1,0.5]];portConstraint=eastwest;dropTarget=0;" vertex="1" parent="244"><mxGeometry y="56" width="200" height="34" as="geometry"/></mxCell><mxCell id="249" value="FK" style="shape=partialRectangle;top=0;left=0;bottom=0;html=1;fillColor=none;align=left;verticalAlign=top;spacingLeft=4;spacingRight=4;whiteSpace=wrap;overflow=hidden;rotatable=0;points=[];portConstraint=eastwest;part=1;" vertex="1" connectable="0" parent="248"><mxGeometry width="56" height="34" as="geometry"/></mxCell><mxCell id="250" value="internalContext" style="shape=partialRectangle;top=0;left=0;right=0;bottom=0;html=1;align=left;verticalAlign=top;fillColor=none;spacingLeft=60;spacingRight=4;whiteSpace=wrap;overflow=hidden;rotatable=0;points=[[0,0.5],[1,0.5]];portConstraint=eastwest;dropTarget=0;" vertex="1" parent="244"><mxGeometry y="90" width="200" height="34" as="geometry"/></mxCell><mxCell id="251" value="FK" style="shape=partialRectangle;top=0;left=0;bottom=0;html=1;fillColor=none;align=left;verticalAlign=top;spacingLeft=4;spacingRight=4;whiteSpace=wrap;overflow=hidden;rotatable=0;points=[];portConstraint=eastwest;part=1;" vertex="1" connectable="0" parent="250"><mxGeometry width="56" height="34" as="geometry"/></mxCell><mxCell id="253" style="edgeStyle=orthogonalEdgeStyle;rounded=0;html=1;exitX=1;exitY=0.5;entryX=0;entryY=0.5;startArrow=ERone;startFill=0;endArrow=ERoneToMany;endFill=0;jettySize=auto;orthogonalLoop=1;" edge="1" parent="1" source="238" target="248"><mxGeometry relative="1" as="geometry"><Array as="points"><mxPoint x="1441" y="474"/><mxPoint x="1441" y="600"/><mxPoint x="1121" y="600"/><mxPoint x="1121" y="714"/></Array></mxGeometry></mxCell><mxCell id="254" style="edgeStyle=orthogonalEdgeStyle;rounded=0;html=1;exitX=1;exitY=0.5;entryX=0;entryY=0.5;startArrow=ERone;startFill=0;endArrow=ERoneToMany;endFill=0;jettySize=auto;orthogonalLoop=1;" edge="1" parent="1" source="240" target="250"><mxGeometry relative="1" as="geometry"><Array as="points"><mxPoint x="1381" y="508"/><mxPoint x="1381" y="560"/><mxPoint x="1081" y="560"/><mxPoint x="1081" y="748"/></Array></mxGeometry></mxCell><mxCell id="266" style="edgeStyle=orthogonalEdgeStyle;rounded=0;html=1;exitX=0;exitY=0.5;startArrow=ERone;startFill=0;endArrow=ERoneToMany;endFill=0;jettySize=auto;orthogonalLoop=1;entryX=0;entryY=0.5;" edge="1" parent="1" source="261" target="270"><mxGeometry relative="1" as="geometry"><mxPoint x="280" y="930" as="targetPoint"/><Array as="points"><mxPoint x="280" y="798"/><mxPoint x="280" y="932"/></Array></mxGeometry></mxCell><mxCell id="267" value="External_InternalTask" style="swimlane;html=1;fontStyle=0;childLayout=stackLayout;horizontal=1;startSize=26;fillColor=#f8cecc;horizontalStack=0;resizeParent=1;resizeLast=0;collapsible=1;marginBottom=0;swimlaneFillColor=#ffffff;align=center;rounded=0;shadow=0;comic=0;labelBackgroundColor=none;strokeColor=#b85450;strokeWidth=1;fontFamily=Verdana;fontSize=14;fontColor=#000000;" vertex="1" parent="1"><mxGeometry x="882" y="836" width="199" height="120" as="geometry"/></mxCell><mxCell id="268" value="externalTask" style="shape=partialRectangle;top=0;left=0;right=0;bottom=0;html=1;align=left;verticalAlign=top;fillColor=none;spacingLeft=60;spacingRight=4;whiteSpace=wrap;overflow=hidden;rotatable=0;points=[[0,0.5],[1,0.5]];portConstraint=eastwest;dropTarget=0;" vertex="1" parent="267"><mxGeometry y="26" width="199" height="44" as="geometry"/></mxCell><mxCell id="269" value="FK" style="shape=partialRectangle;top=0;left=0;bottom=0;html=1;fillColor=none;align=left;verticalAlign=top;spacingLeft=4;spacingRight=4;whiteSpace=wrap;overflow=hidden;rotatable=0;points=[];portConstraint=eastwest;part=1;" vertex="1" connectable="0" parent="268"><mxGeometry width="56" height="44" as="geometry"/></mxCell><mxCell id="270" value="internalTask" style="shape=partialRectangle;top=0;left=0;right=0;bottom=0;html=1;align=left;verticalAlign=top;fillColor=none;spacingLeft=60;spacingRight=4;whiteSpace=wrap;overflow=hidden;rotatable=0;points=[[0,0.5],[1,0.5]];portConstraint=eastwest;dropTarget=0;" vertex="1" parent="267"><mxGeometry y="70" width="199" height="50" as="geometry"/></mxCell><mxCell id="271" value="FK" style="shape=partialRectangle;top=0;left=0;bottom=0;html=1;fillColor=none;align=left;verticalAlign=top;spacingLeft=4;spacingRight=4;whiteSpace=wrap;overflow=hidden;rotatable=0;points=[];portConstraint=eastwest;part=1;" vertex="1" connectable="0" parent="270"><mxGeometry width="56" height="50" as="geometry"/></mxCell><mxCell id="272" style="edgeStyle=orthogonalEdgeStyle;rounded=0;html=1;exitX=0;exitY=0.5;entryX=0;entryY=0.5;startArrow=ERone;startFill=0;endArrow=ERoneToMany;endFill=0;jettySize=auto;orthogonalLoop=1;" edge="1" parent="1" source="263" target="268"><mxGeometry relative="1" as="geometry"><Array as="points"><mxPoint x="320" y="836"/><mxPoint x="320" y="884"/></Array></mxGeometry></mxCell></root></mxGraphModel>